__init__.py
agi_cluster/agi_distributor/__init__.py
agi_cluster/agi_distributor/agi_distributor.py
agi_cluster/agi_distributor/cli.py
agi_cluster-2025.12.19.dist-info/licenses/LICENSE
agi_cluster-2025.12.19.dist-info/METADATA
agi_cluster-2025.12.19.dist-info/WHEEL
agi_cluster-2025.12.19.dist-info/top_level.txt
agi_cluster-2025.12.19.dist-info/RECORD
