Metadata-Version: 2.4
Name: agi-cluster
Version: 2025.12.19
Summary: agi-cluster a framework for AGI
Author-email: Jean-Pierre Morard <focus@thalesgroup.com>
Project-URL: Documentation, https://thalesgroup.github.io/agilab
Project-URL: Source, https://github.com/ThalesGroup/agilab/tree/main/src/agilab/core/agi-cluster
Project-URL: Tracker, https://github.com/ThalesGroup/agilab/issues
Keywords: asyncio,dask,rapids,distributed,cython,cluster,dataframe,dataset,loadbalancing,agi,datascience
Classifier: Intended Audience :: Developers
Classifier: Development Status :: 3 - Alpha
Classifier: Programming Language :: Python :: 3
Classifier: Programming Language :: Python :: 3.11
Classifier: Programming Language :: Python :: 3.12
Classifier: Programming Language :: Python :: 3.13
Classifier: Operating System :: MacOS
Classifier: Operating System :: Microsoft :: Windows
Classifier: Operating System :: POSIX :: Linux
Requires-Python: >=3.11
License-File: LICENSE
Requires-Dist: astor
Requires-Dist: asyncssh
Requires-Dist: cython
Requires-Dist: dask[distributed]
Requires-Dist: humanize
Requires-Dist: ipython
Requires-Dist: jupyter
Requires-Dist: msgpack
Requires-Dist: mypy
Requires-Dist: numba
Requires-Dist: parso
Requires-Dist: pathspec
Requires-Dist: psutil
Requires-Dist: py7zr
Requires-Dist: pydantic
Requires-Dist: python-dotenv
Requires-Dist: requests
Requires-Dist: scp
Requires-Dist: scikit-learn
Requires-Dist: scipy==1.15.2
Requires-Dist: setuptools
Requires-Dist: tomli
Requires-Dist: tomlkit
Requires-Dist: typing-inspection>=0.4.1
Requires-Dist: wheel
Requires-Dist: cmake>=3.29
Dynamic: license-file
